{"metas": [{"id": "CH_MTV_MAX_FINLAND", "type": "tv", "name": "MTV MAX FINLAND", "poster": "https://freeshot.live/upload/source/mtv-max-fi-logo.png", "description": "FREESHOT SCANDINAVIA KATEGORISINDE YAYIN."}, {"id": "CH_SPORT_LIVE_DENMARK", "type": "tv", "name": "SPORT LIVE DENMARK", "poster": "https://freeshot.live/upload/source/SPORTLIVE-logo.png", "description": "FREESHOT SCANDINAVIA KATEGORISINDE YAYIN."}, {"id": "CH_VIASAT_SPORT_1_SWEDEN", "type": "tv", "name": "VIASAT SPORT 1 SWEDEN", "poster": "https://freeshot.live/upload/source/Viasat-Sport-1-Sweden.png", "description": "FREESHOT SCANDINAVIA KATEGORISINDE YAYIN."}]}